{"0473":[{"oldKey":"12-107-03433","oldWardCode":"03433","oldWardType":null,"oldName":"Thị trấn Mường Tè","oldDistrictKey":"12-107","oldDistrictName":"Huyện Mường Tè","oldProvinceCode":"12","oldProvinceName":"Tỉnh Lai Châu","note":""},{"oldKey":"12-107-03445","oldWardCode":"03445","oldWardType":"xã","oldName":"Xã Mường Tè","oldDistrictKey":"12-107","oldDistrictName":"Huyện Mường Tè","oldProvinceCode":"12","oldProvinceName":"Tỉnh Lai Châu","note":""}],"0479":[{"oldKey":"12-112-03473","oldWardCode":"03473","oldWardType":"xã","oldName":"Xã Nậm Chà","oldDistrictKey":"12-112","oldDistrictName":"Huyện Nậm Nhùn","oldProvinceCode":"12","oldProvinceName":"Tỉnh Lai Châu","note":""},{"oldKey":"12-108-03526","oldWardCode":"03526","oldWardType":"xã","oldName":"Xã Nậm Cha","oldDistrictKey":"12-108","oldDistrictName":"Huyện Sìn Hồ","oldProvinceCode":"12","oldProvinceName":"Tỉnh Lai Châu","note":""}]}