{"2379":[{"oldKey":"68-673-24835","oldWardCode":"24835","oldWardType":"xã","oldName":"Xã Lộc Thanh","oldDistrictKey":"68-673","oldDistrictName":"Thành phố Bảo Lộc","oldProvinceCode":"68","oldProvinceName":"Tỉnh Lâm Đồng","note":""},{"oldKey":"68-680-25090","oldWardCode":"25090","oldWardType":"xã","oldName":"Xã Lộc Thành","oldDistrictKey":"68-680","oldDistrictName":"Huyện Bảo Lâm","oldProvinceCode":"68","oldProvinceName":"Tỉnh Lâm Đồng","note":""}],"2419":[{"oldKey":"68-679-25012","oldWardCode":"25012","oldWardType":"xã","oldName":"Xã Tân Nghĩa","oldDistrictKey":"68-679","oldDistrictName":"Huyện Di Linh","oldProvinceCode":"68","oldProvinceName":"Tỉnh Lâm Đồng","note":""},{"oldKey":"60-601-23236","oldWardCode":"23236","oldWardType":null,"oldName":"Thị trấn Tân Nghĩa","oldDistrictKey":"60-601","oldDistrictName":"Huyện Hàm Tân","oldProvinceCode":"60","oldProvinceName":"Tỉnh Bình Thuận","note":""}],"2431":[{"oldKey":"60-596-23053","oldWardCode":"23053","oldWardType":"xã","oldName":"Xã Hòa Thắng","oldDistrictKey":"60-596","oldDistrictName":"Huyện Bắc Bình","oldProvinceCode":"60","oldProvinceName":"Tỉnh Bình Thuận","note":""}],"2440":[{"oldKey":"68-678-24970","oldWardCode":"24970","oldWardType":"xã","oldName":"Xã Bình Thạnh","oldDistrictKey":"68-678","oldDistrictName":"Huyện Đức Trọng","oldProvinceCode":"68","oldProvinceName":"Tỉnh Lâm Đồng","note":""},{"oldKey":"60-595-22999","oldWardCode":"22999","oldWardType":"xã","oldName":"Xã Bình Thạnh","oldDistrictKey":"60-595","oldDistrictName":"Huyện Tuy Phong","oldProvinceCode":"60","oldProvinceName":"Tỉnh Bình Thuận","note":""}],"2459":[{"oldKey":"68-676-24907","oldWardCode":"24907","oldWardType":"xã","oldName":"Xã Tân Thanh","oldDistrictKey":"68-676","oldDistrictName":"Huyện Lâm Hà","oldProvinceCode":"68","oldProvinceName":"Tỉnh Lâm Đồng","note":""},{"oldKey":"68-678-24979","oldWardCode":"24979","oldWardType":"xã","oldName":"Xã Tân Thành","oldDistrictKey":"68-678","oldDistrictName":"Huyện Đức Trọng","oldProvinceCode":"68","oldProvinceName":"Tỉnh Lâm Đồng","note":""},{"oldKey":"67-664-24699","oldWardCode":"24699","oldWardType":"xã","oldName":"Xã Tân Thành","oldDistrictKey":"67-664","oldDistrictName":"Huyện Krông Nô","oldProvinceCode":"67","oldProvinceName":"Tỉnh Đắk Nông","note":""},{"oldKey":"60-598-23146","oldWardCode":"23146","oldWardType":"xã","oldName":"Xã Tân Thành","oldDistrictKey":"60-598","oldDistrictName":"Huyện Hàm Thuận Nam","oldProvinceCode":"60","oldProvinceName":"Tỉnh Bình Thuận","note":""}],"2471":[{"oldKey":"60-596-23047","oldWardCode":"23047","oldWardType":"xã","oldName":"Xã Bình Tân","oldDistrictKey":"60-596","oldDistrictName":"Huyện Bắc Bình","oldProvinceCode":"60","oldProvinceName":"Tỉnh Bình Thuận","note":""},{"oldKey":"60-594-23237","oldWardCode":"23237","oldWardType":"phường","oldName":"Phường Bình Tân","oldDistrictKey":"60-594","oldDistrictName":"Thị xã La Gi","oldProvinceCode":"60","oldProvinceName":"Tỉnh Bình Thuận","note":""}],"2476":[{"oldKey":"68-676-24916","oldWardCode":"24916","oldWardType":"xã","oldName":"Xã Tân Hà","oldDistrictKey":"68-676","oldDistrictName":"Huyện Lâm Hà","oldProvinceCode":"68","oldProvinceName":"Tỉnh Lâm Đồng","note":""},{"oldKey":"60-601-23257","oldWardCode":"23257","oldWardType":"xã","oldName":"Xã Tân Hà","oldDistrictKey":"60-601","oldDistrictName":"Huyện Hàm Tân","oldProvinceCode":"60","oldProvinceName":"Tỉnh Bình Thuận","note":""}],"2478":[{"oldKey":"68-676-24907","oldWardCode":"24907","oldWardType":"xã","oldName":"Xã Tân Thanh","oldDistrictKey":"68-676","oldDistrictName":"Huyện Lâm Hà","oldProvinceCode":"68","oldProvinceName":"Tỉnh Lâm Đồng","note":""},{"oldKey":"68-678-24979","oldWardCode":"24979","oldWardType":"xã","oldName":"Xã Tân Thành","oldDistrictKey":"68-678","oldDistrictName":"Huyện Đức Trọng","oldProvinceCode":"68","oldProvinceName":"Tỉnh Lâm Đồng","note":""},{"oldKey":"67-664-24699","oldWardCode":"24699","oldWardType":"xã","oldName":"Xã Tân Thành","oldDistrictKey":"67-664","oldDistrictName":"Huyện Krông Nô","oldProvinceCode":"67","oldProvinceName":"Tỉnh Đắk Nông","note":""},{"oldKey":"60-598-23146","oldWardCode":"23146","oldWardType":"xã","oldName":"Xã Tân Thành","oldDistrictKey":"60-598","oldDistrictName":"Huyện Hàm Thuận Nam","oldProvinceCode":"60","oldProvinceName":"Tỉnh Bình Thuận","note":""}],"2481":[{"oldKey":"68-676-24907","oldWardCode":"24907","oldWardType":"xã","oldName":"Xã Tân Thanh","oldDistrictKey":"68-676","oldDistrictName":"Huyện Lâm Hà","oldProvinceCode":"68","oldProvinceName":"Tỉnh Lâm Đồng","note":""},{"oldKey":"68-678-24979","oldWardCode":"24979","oldWardType":"xã","oldName":"Xã Tân Thành","oldDistrictKey":"68-678","oldDistrictName":"Huyện Đức Trọng","oldProvinceCode":"68","oldProvinceName":"Tỉnh Lâm Đồng","note":""},{"oldKey":"67-664-24699","oldWardCode":"24699","oldWardType":"xã","oldName":"Xã Tân Thành","oldDistrictKey":"67-664","oldDistrictName":"Huyện Krông Nô","oldProvinceCode":"67","oldProvinceName":"Tỉnh Đắk Nông","note":""},{"oldKey":"60-598-23146","oldWardCode":"23146","oldWardType":"xã","oldName":"Xã Tân Thành","oldDistrictKey":"60-598","oldDistrictName":"Huyện Hàm Thuận Nam","oldProvinceCode":"60","oldProvinceName":"Tỉnh Bình Thuận","note":""}],"2486":[{"oldKey":"68-676-24916","oldWardCode":"24916","oldWardType":"xã","oldName":"Xã Tân Hà","oldDistrictKey":"68-676","oldDistrictName":"Huyện Lâm Hà","oldProvinceCode":"68","oldProvinceName":"Tỉnh Lâm Đồng","note":""},{"oldKey":"60-600-23221","oldWardCode":"23221","oldWardType":"xã","oldName":"Xã Tân Hà","oldDistrictKey":"60-600","oldDistrictName":"Huyện Đức Linh","oldProvinceCode":"60","oldProvinceName":"Tỉnh Bình Thuận","note":""},{"oldKey":"60-601-23257","oldWardCode":"23257","oldWardType":"xã","oldName":"Xã Tân Hà","oldDistrictKey":"60-601","oldDistrictName":"Huyện Hàm Tân","oldProvinceCode":"60","oldProvinceName":"Tỉnh Bình Thuận","note":""}],"2489":[{"oldKey":"60-595-22978","oldWardCode":"22978","oldWardType":"xã","oldName":"Xã Phong Phú","oldDistrictKey":"60-595","oldDistrictName":"Huyện Tuy Phong","oldProvinceCode":"60","oldProvinceName":"Tỉnh Bình Thuận","note":""}],"2492":[{"oldKey":"68-673-24823","oldWardCode":"24823","oldWardType":"phường","oldName":"Phường 1","oldDistrictKey":"68-673","oldDistrictName":"Thành phố Bảo Lộc","oldProvinceCode":"68","oldProvinceName":"Tỉnh Lâm Đồng","note":""},{"oldKey":"68-673-24820","oldWardCode":"24820","oldWardType":"phường","oldName":"Phường 2","oldDistrictKey":"68-673","oldDistrictName":"Thành phố Bảo Lộc","oldProvinceCode":"68","oldProvinceName":"Tỉnh Lâm Đồng","note":""}]}