[{"code":"3292","type":"xã","name":"An Trạch","districtCode":"3291"},{"code":"3293","type":"phường","name":"An Xuyên","districtCode":"3291"},{"code":"3294","type":"phường","name":"Bạc Liêu","districtCode":"3291"},{"code":"3295","type":"xã","name":"Biển Bạch","districtCode":"3291"},{"code":"3296","type":"xã","name":"Cái Đôi Vàm","districtCode":"3291"},{"code":"3297","type":"xã","name":"Cái Nước","districtCode":"3291"},{"code":"3298","type":"xã","name":"Châu Thới","districtCode":"3291"},{"code":"3299","type":"xã","name":"Đá Bạc","districtCode":"3291"},{"code":"3300","type":"xã","name":"Đầm Dơi","districtCode":"3291"},{"code":"3301","type":"xã","name":"Đất Mới","districtCode":"3291"},{"code":"3302","type":"xã","name":"Đất Mũi","districtCode":"3291"},{"code":"3303","type":"xã","name":"Định Thành","districtCode":"3291"},{"code":"3304","type":"xã","name":"Đông Hải","districtCode":"3291"},{"code":"3305","type":"xã","name":"Gành Hào","districtCode":"3291"},{"code":"3306","type":"phường","name":"Giá Rai","districtCode":"3291"},{"code":"3307","type":"phường","name":"Hiệp Thành","districtCode":"3291"},{"code":"3309","type":"xã","name":"Hoà Bình","districtCode":"3291"},{"code":"3310","type":"phường","name":"Hoà Thành","districtCode":"3291"},{"code":"3308","type":"xã","name":"Hồ Thị Kỷ","districtCode":"3291"},{"code":"3311","type":"xã","name":"Hồng Dân","districtCode":"3291"},{"code":"3312","type":"xã","name":"Hưng Hội","districtCode":"3291"},{"code":"3313","type":"xã","name":"Hưng Mỹ","districtCode":"3291"},{"code":"3314","type":"xã","name":"Khánh An","districtCode":"3291"},{"code":"3315","type":"xã","name":"Khánh Bình","districtCode":"3291"},{"code":"3316","type":"xã","name":"Khánh Hưng","districtCode":"3291"},{"code":"3317","type":"xã","name":"Khánh Lâm","districtCode":"3291"},{"code":"3318","type":"phường","name":"Láng Tròn","districtCode":"3291"},{"code":"3319","type":"xã","name":"Long Điền","districtCode":"3291"},{"code":"3320","type":"xã","name":"Lương Thế Trân","districtCode":"3291"},{"code":"3321","type":"phường","name":"Lý Văn Lâm","districtCode":"3291"},{"code":"3322","type":"xã","name":"Năm Căn","districtCode":"3291"},{"code":"3323","type":"xã","name":"Nguyễn Phích","districtCode":"3291"},{"code":"3324","type":"xã","name":"Nguyễn Việt Khái","districtCode":"3291"},{"code":"3325","type":"xã","name":"Ninh Quới","districtCode":"3291"},{"code":"3326","type":"xã","name":"Ninh Thạnh Lợi","districtCode":"3291"},{"code":"3327","type":"xã","name":"Phan Ngọc Hiển","districtCode":"3291"},{"code":"3328","type":"xã","name":"Phong Hiệp","districtCode":"3291"},{"code":"3329","type":"xã","name":"Phong Thạnh","districtCode":"3291"},{"code":"3330","type":"xã","name":"Phú Mỹ","districtCode":"3291"},{"code":"3331","type":"xã","name":"Phú Tân","districtCode":"3291"},{"code":"3332","type":"xã","name":"Phước Long","districtCode":"3291"},{"code":"3333","type":"xã","name":"Quách Phẩm","districtCode":"3291"},{"code":"3334","type":"xã","name":"Sông Đốc","districtCode":"3291"},{"code":"3335","type":"xã","name":"Tạ An Khương","districtCode":"3291"},{"code":"3336","type":"xã","name":"Tam Giang","districtCode":"3291"},{"code":"3337","type":"xã","name":"Tân Ân","districtCode":"3291"},{"code":"3338","type":"xã","name":"Tân Hưng","districtCode":"3291"},{"code":"3339","type":"xã","name":"Tân Lộc","districtCode":"3291"},{"code":"3340","type":"phường","name":"Tân Thành","districtCode":"3291"},{"code":"3341","type":"xã","name":"Tân Thuận","districtCode":"3291"},{"code":"3342","type":"xã","name":"Tân Tiến","districtCode":"3291"},{"code":"3343","type":"xã","name":"Thanh Tùng","districtCode":"3291"},{"code":"3344","type":"xã","name":"Thới Bình","districtCode":"3291"},{"code":"3345","type":"xã","name":"Trần Phán","districtCode":"3291"},{"code":"3346","type":"xã","name":"Trần Văn Thời","districtCode":"3291"},{"code":"3347","type":"xã","name":"Trí Phải","districtCode":"3291"},{"code":"3348","type":"xã","name":"U Minh","districtCode":"3291"},{"code":"3349","type":"xã","name":"Vĩnh Hậu","districtCode":"3291"},{"code":"3350","type":"xã","name":"Vĩnh Lộc","districtCode":"3291"},{"code":"3351","type":"xã","name":"Vĩnh Lợi","districtCode":"3291"},{"code":"3352","type":"xã","name":"Vĩnh Mỹ","districtCode":"3291"},{"code":"3353","type":"xã","name":"Vĩnh Phước","districtCode":"3291"},{"code":"3354","type":"xã","name":"Vĩnh Thanh","districtCode":"3291"},{"code":"3355","type":"phường","name":"Vĩnh Trạch","districtCode":"3291"}]