{"0741":[{"oldKey":"22-200-06895","oldWardCode":"06895","oldWardType":null,"oldName":"Thị trấn Đầm Hà","oldDistrictKey":"22-200","oldDistrictName":"Huyện Đầm Hà","oldProvinceCode":"22","oldProvinceName":"Tỉnh Quảng Ninh","note":""},{"oldKey":"22-200-06916","oldWardCode":"06916","oldWardType":"xã","oldName":"Xã Đầm Hà","oldDistrictKey":"22-200","oldDistrictName":"Huyện Đầm Hà","oldProvinceCode":"22","oldProvinceName":"Tỉnh Quảng Ninh","note":""}],"0745":[{"oldKey":"22-205-07093","oldWardCode":"07093","oldWardType":"phường","oldName":"Phường Đức Chính","oldDistrictKey":"22-205","oldDistrictName":"Thành phố Đông Triều","oldProvinceCode":"22","oldProvinceName":"Tỉnh Quảng Ninh","note":""}],"0751":[{"oldKey":"22-199-06886","oldWardCode":"06886","oldWardType":"xã","oldName":"Xã Hải Lạng","oldDistrictKey":"22-199","oldDistrictName":"Huyện Tiên Yên","oldProvinceCode":"22","oldProvinceName":"Tỉnh Quảng Ninh","note":""}],"0752":[{"oldKey":"22-199-06886","oldWardCode":"06886","oldWardType":"xã","oldName":"Xã Hải Lạng","oldDistrictKey":"22-199","oldDistrictName":"Huyện Tiên Yên","oldProvinceCode":"22","oldProvinceName":"Tỉnh Quảng Ninh","note":""},{"oldKey":"22-194-06742","oldWardCode":"06742","oldWardType":"phường","oldName":"Phường Hải Hoà","oldDistrictKey":"22-194","oldDistrictName":"Thành phố Móng Cái","oldProvinceCode":"22","oldProvinceName":"Tỉnh Quảng Ninh","note":""},{"oldKey":"22-195-06799","oldWardCode":"06799","oldWardType":"xã","oldName":"Xã Hải Hòa","oldDistrictKey":"22-195","oldDistrictName":"Thành phố Cẩm Phả","oldProvinceCode":"22","oldProvinceName":"Tỉnh Quảng Ninh","note":""}],"0761":[{"oldKey":"22-206-07180","oldWardCode":"07180","oldWardType":"xã","oldName":"Xã Liên Hòa","oldDistrictKey":"22-206","oldDistrictName":"Thị xã Quảng Yên","oldProvinceCode":"22","oldProvinceName":"Tỉnh Quảng Ninh","note":""}],"0765":[{"oldKey":"22-194-06742","oldWardCode":"06742","oldWardType":"phường","oldName":"Phường Hải Hoà","oldDistrictKey":"22-194","oldDistrictName":"Thành phố Móng Cái","oldProvinceCode":"22","oldProvinceName":"Tỉnh Quảng Ninh","note":""},{"oldKey":"22-195-06799","oldWardCode":"06799","oldWardType":"xã","oldName":"Xã Hải Hòa","oldDistrictKey":"22-195","oldDistrictName":"Thành phố Cẩm Phả","oldProvinceCode":"22","oldProvinceName":"Tỉnh Quảng Ninh","note":""}],"0771":[{"oldKey":"22-201-06946","oldWardCode":"06946","oldWardType":"xã","oldName":"Xã Quảng Long","oldDistrictKey":"22-201","oldDistrictName":"Huyện Hải Hà","oldProvinceCode":"22","oldProvinceName":"Tỉnh Quảng Ninh","note":""}],"0776":[{"oldKey":"22-193-07042","oldWardCode":"07042","oldWardType":"xã","oldName":"Xã Đồng Lâm","oldDistrictKey":"22-193","oldDistrictName":"Thành phố Hạ Long","oldProvinceCode":"22","oldProvinceName":"Tỉnh Quảng Ninh","note":""}],"0777":[{"oldKey":"22-199-06880","oldWardCode":"06880","oldWardType":"xã","oldName":"Xã Yên Than","oldDistrictKey":"22-199","oldDistrictName":"Huyện Tiên Yên","oldProvinceCode":"22","oldProvinceName":"Tỉnh Quảng Ninh","note":""},{"oldKey":"22-199-06868","oldWardCode":"06868","oldWardType":"xã","oldName":"Xã Đại Dực","oldDistrictKey":"22-199","oldDistrictName":"Huyện Tiên Yên","oldProvinceCode":"22","oldProvinceName":"Tỉnh Quảng Ninh","note":""},{"oldKey":"22-199-06877","oldWardCode":"06877","oldWardType":"xã","oldName":"Xã Đông Ngũ","oldDistrictKey":"22-199","oldDistrictName":"Huyện Tiên Yên","oldProvinceCode":"22","oldProvinceName":"Tỉnh Quảng Ninh","note":""},{"oldKey":"22-198-06853","oldWardCode":"06853","oldWardType":"xã","oldName":"Xã Vô Ngại","oldDistrictKey":"22-198","oldDistrictName":"Huyện Bình Liêu","oldProvinceCode":"22","oldProvinceName":"Tỉnh Quảng Ninh","note":""}],"0779":[{"oldKey":"22-196-06811","oldWardCode":"06811","oldWardType":"phường","oldName":"Phường Thanh Sơn","oldDistrictKey":"22-196","oldDistrictName":"Thành phố Uông Bí","oldProvinceCode":"22","oldProvinceName":"Tỉnh Quảng Ninh","note":""},{"oldKey":"22-202-06973","oldWardCode":"06973","oldWardType":"xã","oldName":"Xã Thanh Sơn","oldDistrictKey":"22-202","oldDistrictName":"Huyện Ba Chẽ","oldProvinceCode":"22","oldProvinceName":"Tỉnh Quảng Ninh","note":""}],"0781":[{"oldKey":"22-194-06727","oldWardCode":"06727","oldWardType":"xã","oldName":"Xã Bắc Sơn","oldDistrictKey":"22-194","oldDistrictName":"Thành phố Móng Cái","oldProvinceCode":"22","oldProvinceName":"Tỉnh Quảng Ninh","note":""},{"oldKey":"22-196-06814","oldWardCode":"06814","oldWardType":"phường","oldName":"Phường Bắc Sơn","oldDistrictKey":"22-196","oldDistrictName":"Thành phố Uông Bí","oldProvinceCode":"22","oldProvinceName":"Tỉnh Quảng Ninh","note":""},{"oldKey":"22-196-06820","oldWardCode":"06820","oldWardType":"phường","oldName":"Phường Trưng Vương","oldDistrictKey":"22-196","oldDistrictName":"Thành phố Uông Bí","oldProvinceCode":"22","oldProvinceName":"Tỉnh Quảng Ninh","note":""}],"0782":[{"oldKey":"22-193-06655","oldWardCode":"06655","oldWardType":"phường","oldName":"Phường Hà Khẩu","oldDistrictKey":"22-193","oldDistrictName":"Thành phố Hạ Long","oldProvinceCode":"22","oldProvinceName":"Tỉnh Quảng Ninh","note":""}],"0731":[{"oldKey":"22-205-07090","oldWardCode":"07090","oldWardType":null,"oldName":"Phường Bình Dương","oldDistrictKey":"22-205","oldDistrictName":"Thành phố Đông Triều","oldProvinceCode":"22","oldProvinceName":"Tỉnh Quảng Ninh","note":""},{"oldKey":"22-205-07075","oldWardCode":"07075","oldWardType":null,"oldName":"Xã An Sinh","oldDistrictKey":"22-205","oldDistrictName":"Thành phố Đông Triều","oldProvinceCode":"22","oldProvinceName":"Tỉnh Quảng Ninh","note":""},{"oldKey":"22-205-07084","oldWardCode":"07084","oldWardType":null,"oldName":"Xã Việt Dân","oldDistrictKey":"22-205","oldDistrictName":"Thành phố Đông Triều","oldProvinceCode":"22","oldProvinceName":"Tỉnh Quảng Ninh","note":""},{"oldKey":"22-205-07093","oldWardCode":"07093","oldWardType":null,"oldName":"Phường Đức Chính","oldDistrictKey":"22-205","oldDistrictName":"Thành phố Đông Triều","oldProvinceCode":"22","oldProvinceName":"Tỉnh Quảng Ninh","note":""}],"0732":[{"oldKey":"22-202-06970","oldWardCode":"06970","oldWardType":null,"oldName":"Thị trấn Ba Chẽ","oldDistrictKey":"22-202","oldDistrictName":"Huyện Ba Chẽ","oldProvinceCode":"22","oldProvinceName":"Tỉnh Quảng Ninh","note":""},{"oldKey":"22-196-06811","oldWardCode":"06811","oldWardType":null,"oldName":"Phường Thanh Sơn","oldDistrictKey":"22-196","oldDistrictName":"Thành phố Uông Bí","oldProvinceCode":"22","oldProvinceName":"Tỉnh Quảng Ninh","note":""},{"oldKey":"22-202-06973","oldWardCode":"06973","oldWardType":null,"oldName":"Xã Thanh Sơn","oldDistrictKey":"22-202","oldDistrictName":"Huyện Ba Chẽ","oldProvinceCode":"22","oldProvinceName":"Tỉnh Quảng Ninh","note":""},{"oldKey":"22-202-06982","oldWardCode":"06982","oldWardType":null,"oldName":"Xã Nam Sơn","oldDistrictKey":"22-202","oldDistrictName":"Huyện Ba Chẽ","oldProvinceCode":"22","oldProvinceName":"Tỉnh Quảng Ninh","note":""},{"oldKey":"22-202-06988","oldWardCode":"06988","oldWardType":null,"oldName":"Xã Đồn Đạc","oldDistrictKey":"22-202","oldDistrictName":"Huyện Ba Chẽ","oldProvinceCode":"22","oldProvinceName":"Tỉnh Quảng Ninh","note":""},{"oldKey":"22-199-06886","oldWardCode":"06886","oldWardType":null,"oldName":"Xã Hải Lạng","oldDistrictKey":"22-199","oldDistrictName":"Huyện Tiên Yên","oldProvinceCode":"22","oldProvinceName":"Tỉnh Quảng Ninh","note":""}],"0733":[{"oldKey":"22-193-06679","oldWardCode":"06679","oldWardType":null,"oldName":"Phường Hùng Thắng","oldDistrictKey":"22-193","oldDistrictName":"Thành phố Hạ Long","oldProvinceCode":"22","oldProvinceName":"Tỉnh Quảng Ninh","note":""},{"oldKey":"22-193-06673","oldWardCode":"06673","oldWardType":null,"oldName":"Phường Bãi Cháy","oldDistrictKey":"22-193","oldDistrictName":"Thành phố Hạ Long","oldProvinceCode":"22","oldProvinceName":"Tỉnh Quảng Ninh","note":""}],"0734":[{"oldKey":"22-205-07096","oldWardCode":"07096","oldWardType":null,"oldName":"Phường Tràng An","oldDistrictKey":"22-205","oldDistrictName":"Thành phố Đông Triều","oldProvinceCode":"22","oldProvinceName":"Tỉnh Quảng Ninh","note":""},{"oldKey":"22-205-07081","oldWardCode":"07081","oldWardType":null,"oldName":"Phường Bình Khê","oldDistrictKey":"22-205","oldDistrictName":"Thành phố Đông Triều","oldProvinceCode":"22","oldProvinceName":"Tỉnh Quảng Ninh","note":""},{"oldKey":"22-205-07078","oldWardCode":"07078","oldWardType":null,"oldName":"Xã Tràng Lương","oldDistrictKey":"22-205","oldDistrictName":"Thành phố Đông Triều","oldProvinceCode":"22","oldProvinceName":"Tỉnh Quảng Ninh","note":""}],"0735":[{"oldKey":"22-198-06838","oldWardCode":"06838","oldWardType":null,"oldName":"Thị trấn Bình Liêu","oldDistrictKey":"22-198","oldDistrictName":"Huyện Bình Liêu","oldProvinceCode":"22","oldProvinceName":"Tỉnh Quảng Ninh","note":""},{"oldKey":"22-198-06859","oldWardCode":"06859","oldWardType":null,"oldName":"Xã Húc Động","oldDistrictKey":"22-198","oldDistrictName":"Huyện Bình Liêu","oldProvinceCode":"22","oldProvinceName":"Tỉnh Quảng Ninh","note":""},{"oldKey":"22-198-06853","oldWardCode":"06853","oldWardType":null,"oldName":"Xã Vô Ngại","oldDistrictKey":"22-198","oldDistrictName":"Huyện Bình Liêu","oldProvinceCode":"22","oldProvinceName":"Tỉnh Quảng Ninh","note":""}],"0737":[{"oldKey":"22-195-06793","oldWardCode":"06793","oldWardType":null,"oldName":"Phường Cẩm Trung","oldDistrictKey":"22-195","oldDistrictName":"Thành phố Cẩm Phả","oldProvinceCode":"22","oldProvinceName":"Tỉnh Quảng Ninh","note":""},{"oldKey":"22-195-06790","oldWardCode":"06790","oldWardType":null,"oldName":"Phường Cẩm Thành","oldDistrictKey":"22-195","oldDistrictName":"Thành phố Cẩm Phả","oldProvinceCode":"22","oldProvinceName":"Tỉnh Quảng Ninh","note":""},{"oldKey":"22-195-06796","oldWardCode":"06796","oldWardType":null,"oldName":"Phường Cẩm Bình","oldDistrictKey":"22-195","oldDistrictName":"Thành phố Cẩm Phả","oldProvinceCode":"22","oldProvinceName":"Tỉnh Quảng Ninh","note":""},{"oldKey":"22-195-06775","oldWardCode":"06775","oldWardType":null,"oldName":"Phường Cẩm Tây","oldDistrictKey":"22-195","oldDistrictName":"Thành phố Cẩm Phả","oldProvinceCode":"22","oldProvinceName":"Tỉnh Quảng Ninh","note":""},{"oldKey":"22-195-06769","oldWardCode":"06769","oldWardType":null,"oldName":"Phường Cẩm Đông","oldDistrictKey":"22-195","oldDistrictName":"Thành phố Cẩm Phả","oldProvinceCode":"22","oldProvinceName":"Tỉnh Quảng Ninh","note":""}],"0738":[{"oldKey":"22-193-06649","oldWardCode":"06649","oldWardType":null,"oldName":"Phường Hà Khánh","oldDistrictKey":"22-193","oldDistrictName":"Thành phố Hạ Long","oldProvinceCode":"22","oldProvinceName":"Tỉnh Quảng Ninh","note":""},{"oldKey":"22-193-06658","oldWardCode":"06658","oldWardType":null,"oldName":"Phường Cao Xanh","oldDistrictKey":"22-193","oldDistrictName":"Thành phố Hạ Long","oldProvinceCode":"22","oldProvinceName":"Tỉnh Quảng Ninh","note":""}],"0739":[{"oldKey":"22-207-07192","oldWardCode":"07192","oldWardType":null,"oldName":"Thị trấn Cô Tô","oldDistrictKey":"22-207","oldDistrictName":"Huyện Cô Tô","oldProvinceCode":"22","oldProvinceName":"Tỉnh Quảng Ninh","note":""},{"oldKey":"22-207-07195","oldWardCode":"07195","oldWardType":null,"oldName":"Xã Đồng Tiến","oldDistrictKey":"22-207","oldDistrictName":"Huyện Cô Tô","oldProvinceCode":"22","oldProvinceName":"Tỉnh Quảng Ninh","note":""},{"oldKey":"22-207-07198","oldWardCode":"07198","oldWardType":null,"oldName":"Xã Thanh Lân","oldDistrictKey":"22-207","oldDistrictName":"Huyện Cô Tô","oldProvinceCode":"22","oldProvinceName":"Tỉnh Quảng Ninh","note":""}],"0740":[{"oldKey":"22-195-06772","oldWardCode":"06772","oldWardType":null,"oldName":"Phường Cẩm Phú","oldDistrictKey":"22-195","oldDistrictName":"Thành phố Cẩm Phả","oldProvinceCode":"22","oldProvinceName":"Tỉnh Quảng Ninh","note":""},{"oldKey":"22-195-06781","oldWardCode":"06781","oldWardType":null,"oldName":"Phường Cẩm Thịnh","oldDistrictKey":"22-195","oldDistrictName":"Thành phố Cẩm Phả","oldProvinceCode":"22","oldProvinceName":"Tỉnh Quảng Ninh","note":""},{"oldKey":"22-195-06766","oldWardCode":"06766","oldWardType":null,"oldName":"Phường Cẩm Sơn","oldDistrictKey":"22-195","oldDistrictName":"Thành phố Cẩm Phả","oldProvinceCode":"22","oldProvinceName":"Tỉnh Quảng Ninh","note":""},{"oldKey":"22-195-06763","oldWardCode":"06763","oldWardType":null,"oldName":"Phường Cửa Ông","oldDistrictKey":"22-195","oldDistrictName":"Thành phố Cẩm Phả","oldProvinceCode":"22","oldProvinceName":"Tỉnh Quảng Ninh","note":""}],"0742":[{"oldKey":"22-199-06865","oldWardCode":"06865","oldWardType":null,"oldName":"Xã Hà Lâu","oldDistrictKey":"22-199","oldDistrictName":"Huyện Tiên Yên","oldProvinceCode":"22","oldProvinceName":"Tỉnh Quảng Ninh","note":""},{"oldKey":"22-199-06874","oldWardCode":"06874","oldWardType":null,"oldName":"Xã Điền Xá","oldDistrictKey":"22-199","oldDistrictName":"Huyện Tiên Yên","oldProvinceCode":"22","oldProvinceName":"Tỉnh Quảng Ninh","note":""},{"oldKey":"22-199-06880","oldWardCode":"06880","oldWardType":null,"oldName":"Xã Yên Than","oldDistrictKey":"22-199","oldDistrictName":"Huyện Tiên Yên","oldProvinceCode":"22","oldProvinceName":"Tỉnh Quảng Ninh","note":""}],"0743":[{"oldKey":"22-206-07138","oldWardCode":"07138","oldWardType":null,"oldName":"Phường Minh Thành","oldDistrictKey":"22-206","oldDistrictName":"Thị xã Quảng Yên","oldProvinceCode":"22","oldProvinceName":"Tỉnh Quảng Ninh","note":""},{"oldKey":"22-206-07135","oldWardCode":"07135","oldWardType":null,"oldName":"Phường Đông Mai","oldDistrictKey":"22-206","oldDistrictName":"Thị xã Quảng Yên","oldProvinceCode":"22","oldProvinceName":"Tỉnh Quảng Ninh","note":""}],"0744":[{"oldKey":"22-199-06883","oldWardCode":"06883","oldWardType":null,"oldName":"Xã Đông Hải","oldDistrictKey":"22-199","oldDistrictName":"Huyện Tiên Yên","oldProvinceCode":"22","oldProvinceName":"Tỉnh Quảng Ninh","note":""},{"oldKey":"22-199-06868","oldWardCode":"06868","oldWardType":null,"oldName":"Xã Đại Dực","oldDistrictKey":"22-199","oldDistrictName":"Huyện Tiên Yên","oldProvinceCode":"22","oldProvinceName":"Tỉnh Quảng Ninh","note":""},{"oldKey":"22-199-06877","oldWardCode":"06877","oldWardType":null,"oldName":"Xã Đông Ngũ","oldDistrictKey":"22-199","oldDistrictName":"Huyện Tiên Yên","oldProvinceCode":"22","oldProvinceName":"Tỉnh Quảng Ninh","note":""}],"0746":[{"oldKey":"22-201-06928","oldWardCode":"06928","oldWardType":null,"oldName":"Xã Quảng Sơn","oldDistrictKey":"22-201","oldDistrictName":"Huyện Hải Hà","oldProvinceCode":"22","oldProvinceName":"Tỉnh Quảng Ninh","note":""},{"oldKey":"22-201-06949","oldWardCode":"06949","oldWardType":null,"oldName":"Xã Đường Hoa","oldDistrictKey":"22-201","oldDistrictName":"Huyện Hải Hà","oldProvinceCode":"22","oldProvinceName":"Tỉnh Quảng Ninh","note":""},{"oldKey":"22-201-06946","oldWardCode":"06946","oldWardType":null,"oldName":"Xã Quảng Long","oldDistrictKey":"22-201","oldDistrictName":"Huyện Hải Hà","oldProvinceCode":"22","oldProvinceName":"Tỉnh Quảng Ninh","note":""}],"0747":[{"oldKey":"22-206-07159","oldWardCode":"07159","oldWardType":null,"oldName":"Phường Tân An","oldDistrictKey":"22-206","oldDistrictName":"Thị xã Quảng Yên","oldProvinceCode":"22","oldProvinceName":"Tỉnh Quảng Ninh","note":""},{"oldKey":"22-206-07168","oldWardCode":"07168","oldWardType":null,"oldName":"Phường Hà An","oldDistrictKey":"22-206","oldDistrictName":"Thị xã Quảng Yên","oldProvinceCode":"22","oldProvinceName":"Tỉnh Quảng Ninh","note":""},{"oldKey":"22-206-07156","oldWardCode":"07156","oldWardType":null,"oldName":"Xã Hoàng Tân","oldDistrictKey":"22-206","oldDistrictName":"Thị xã Quảng Yên","oldProvinceCode":"22","oldProvinceName":"Tỉnh Quảng Ninh","note":""},{"oldKey":"22-206-07180","oldWardCode":"07180","oldWardType":null,"oldName":"Xã Liên Hòa","oldDistrictKey":"22-206","oldDistrictName":"Thị xã Quảng Yên","oldProvinceCode":"22","oldProvinceName":"Tỉnh Quảng Ninh","note":""}],"0748":[{"oldKey":"22-193-06676","oldWardCode":"06676","oldWardType":null,"oldName":"Phường Cao Thắng","oldDistrictKey":"22-193","oldDistrictName":"Thành phố Hạ Long","oldProvinceCode":"22","oldProvinceName":"Tỉnh Quảng Ninh","note":""},{"oldKey":"22-193-06667","oldWardCode":"06667","oldWardType":null,"oldName":"Phường Hà Trung","oldDistrictKey":"22-193","oldDistrictName":"Thành phố Hạ Long","oldProvinceCode":"22","oldProvinceName":"Tỉnh Quảng Ninh","note":""},{"oldKey":"22-193-06670","oldWardCode":"06670","oldWardType":null,"oldName":"Phường Hà Lầm","oldDistrictKey":"22-193","oldDistrictName":"Thành phố Hạ Long","oldProvinceCode":"22","oldProvinceName":"Tỉnh Quảng Ninh","note":""}],"0749":[{"oldKey":"22-193-06697","oldWardCode":"06697","oldWardType":null,"oldName":"Phường Hồng Hà","oldDistrictKey":"22-193","oldDistrictName":"Thành phố Hạ Long","oldProvinceCode":"22","oldProvinceName":"Tỉnh Quảng Ninh","note":""},{"oldKey":"22-193-06688","oldWardCode":"06688","oldWardType":null,"oldName":"Phường Hồng Hải","oldDistrictKey":"22-193","oldDistrictName":"Thành phố Hạ Long","oldProvinceCode":"22","oldProvinceName":"Tỉnh Quảng Ninh","note":""}],"0750":[{"oldKey":"22-193-06652","oldWardCode":"06652","oldWardType":null,"oldName":"Phường Hà Phong","oldDistrictKey":"22-193","oldDistrictName":"Thành phố Hạ Long","oldProvinceCode":"22","oldProvinceName":"Tỉnh Quảng Ninh","note":""},{"oldKey":"22-193-06664","oldWardCode":"06664","oldWardType":null,"oldName":"Phường Hà Tu","oldDistrictKey":"22-193","oldDistrictName":"Thành phố Hạ Long","oldProvinceCode":"22","oldProvinceName":"Tỉnh Quảng Ninh","note":""}],"0753":[{"oldKey":"22-194-06739","oldWardCode":"06739","oldWardType":null,"oldName":"Xã Quảng Nghĩa","oldDistrictKey":"22-194","oldDistrictName":"Thành phố Móng Cái","oldProvinceCode":"22","oldProvinceName":"Tỉnh Quảng Ninh","note":""},{"oldKey":"22-194-06733","oldWardCode":"06733","oldWardType":null,"oldName":"Xã Hải Tiến","oldDistrictKey":"22-194","oldDistrictName":"Thành phố Móng Cái","oldProvinceCode":"22","oldProvinceName":"Tỉnh Quảng Ninh","note":""}],"0754":[{"oldKey":"22-194-06727","oldWardCode":"06727","oldWardType":null,"oldName":"Xã Bắc Sơn","oldDistrictKey":"22-194","oldDistrictName":"Thành phố Móng Cái","oldProvinceCode":"22","oldProvinceName":"Tỉnh Quảng Ninh","note":""},{"oldKey":"22-196-06814","oldWardCode":"06814","oldWardType":null,"oldName":"Phường Bắc Sơn","oldDistrictKey":"22-196","oldDistrictName":"Thành phố Uông Bí","oldProvinceCode":"22","oldProvinceName":"Tỉnh Quảng Ninh","note":""},{"oldKey":"22-194-06724","oldWardCode":"06724","oldWardType":null,"oldName":"Xã Hải Sơn","oldDistrictKey":"22-194","oldDistrictName":"Thành phố Móng Cái","oldProvinceCode":"22","oldProvinceName":"Tỉnh Quảng Ninh","note":""}],"0755":[{"oldKey":"22-206-07150","oldWardCode":"07150","oldWardType":null,"oldName":"Phường Cộng Hòa","oldDistrictKey":"22-206","oldDistrictName":"Thị xã Quảng Yên","oldProvinceCode":"22","oldProvinceName":"Tỉnh Quảng Ninh","note":""},{"oldKey":"22-206-07144","oldWardCode":"07144","oldWardType":null,"oldName":"Xã Sông Khoai","oldDistrictKey":"22-206","oldDistrictName":"Thị xã Quảng Yên","oldProvinceCode":"22","oldProvinceName":"Tỉnh Quảng Ninh","note":""},{"oldKey":"22-206-07147","oldWardCode":"07147","oldWardType":null,"oldName":"Xã Hiệp Hòa","oldDistrictKey":"22-206","oldDistrictName":"Thị xã Quảng Yên","oldProvinceCode":"22","oldProvinceName":"Tỉnh Quảng Ninh","note":""}],"0756":[{"oldKey":"22-205-07129","oldWardCode":"07129","oldWardType":null,"oldName":"Phường Yên Đức","oldDistrictKey":"22-205","oldDistrictName":"Thành phố Đông Triều","oldProvinceCode":"22","oldProvinceName":"Tỉnh Quảng Ninh","note":""},{"oldKey":"22-205-07114","oldWardCode":"07114","oldWardType":null,"oldName":"Phường Hoàng Quế","oldDistrictKey":"22-205","oldDistrictName":"Thành phố Đông Triều","oldProvinceCode":"22","oldProvinceName":"Tỉnh Quảng Ninh","note":""},{"oldKey":"22-205-07108","oldWardCode":"07108","oldWardType":null,"oldName":"Xã Hồng Thái Tây","oldDistrictKey":"22-205","oldDistrictName":"Thành phố Đông Triều","oldProvinceCode":"22","oldProvinceName":"Tỉnh Quảng Ninh","note":""},{"oldKey":"22-205-07111","oldWardCode":"07111","oldWardType":null,"oldName":"Xã Hồng Thái Đông","oldDistrictKey":"22-205","oldDistrictName":"Thành phố Đông Triều","oldProvinceCode":"22","oldProvinceName":"Tỉnh Quảng Ninh","note":""}],"0757":[{"oldKey":"22-193-07030","oldWardCode":"07030","oldWardType":null,"oldName":"Phường Hoành Bồ","oldDistrictKey":"22-193","oldDistrictName":"Thành phố Hạ Long","oldProvinceCode":"22","oldProvinceName":"Tỉnh Quảng Ninh","note":""},{"oldKey":"22-193-07063","oldWardCode":"07063","oldWardType":null,"oldName":"Xã Sơn Dương","oldDistrictKey":"22-193","oldDistrictName":"Thành phố Hạ Long","oldProvinceCode":"22","oldProvinceName":"Tỉnh Quảng Ninh","note":""},{"oldKey":"22-193-07066","oldWardCode":"07066","oldWardType":null,"oldName":"Xã Lê Lợi","oldDistrictKey":"22-193","oldDistrictName":"Thành phố Hạ Long","oldProvinceCode":"22","oldProvinceName":"Tỉnh Quảng Ninh","note":""},{"oldKey":"22-193-07042","oldWardCode":"07042","oldWardType":null,"oldName":"Xã Đồng Lâm","oldDistrictKey":"22-193","oldDistrictName":"Thành phố Hạ Long","oldProvinceCode":"22","oldProvinceName":"Tỉnh Quảng Ninh","note":""}],"0758":[{"oldKey":"22-198-06847","oldWardCode":"06847","oldWardType":null,"oldName":"Xã Đồng Văn","oldDistrictKey":"22-198","oldDistrictName":"Huyện Bình Liêu","oldProvinceCode":"22","oldProvinceName":"Tỉnh Quảng Ninh","note":""},{"oldKey":"22-198-06841","oldWardCode":"06841","oldWardType":null,"oldName":"Xã Hoành Mô","oldDistrictKey":"22-198","oldDistrictName":"Huyện Bình Liêu","oldProvinceCode":"22","oldProvinceName":"Tỉnh Quảng Ninh","note":""}],"0759":[{"oldKey":"22-193-06694","oldWardCode":"06694","oldWardType":null,"oldName":"Phường Bạch Đằng","oldDistrictKey":"22-193","oldDistrictName":"Thành phố Hạ Long","oldProvinceCode":"22","oldProvinceName":"Tỉnh Quảng Ninh","note":""},{"oldKey":"22-193-06685","oldWardCode":"06685","oldWardType":null,"oldName":"Phường Trần Hưng Đạo","oldDistrictKey":"22-193","oldDistrictName":"Thành phố Hạ Long","oldProvinceCode":"22","oldProvinceName":"Tỉnh Quảng Ninh","note":""},{"oldKey":"22-193-06691","oldWardCode":"06691","oldWardType":null,"oldName":"Phường Hồng Gai","oldDistrictKey":"22-193","oldDistrictName":"Thành phố Hạ Long","oldProvinceCode":"22","oldProvinceName":"Tỉnh Quảng Ninh","note":""}],"0760":[{"oldKey":"22-202-06976","oldWardCode":"06976","oldWardType":null,"oldName":"Xã Thanh Lâm","oldDistrictKey":"22-202","oldDistrictName":"Huyện Ba Chẽ","oldProvinceCode":"22","oldProvinceName":"Tỉnh Quảng Ninh","note":""},{"oldKey":"22-202-06979","oldWardCode":"06979","oldWardType":null,"oldName":"Xã Đạp Thanh","oldDistrictKey":"22-202","oldDistrictName":"Huyện Ba Chẽ","oldProvinceCode":"22","oldProvinceName":"Tỉnh Quảng Ninh","note":""},{"oldKey":"22-193-07033","oldWardCode":"07033","oldWardType":null,"oldName":"Xã Kỳ Thượng","oldDistrictKey":"22-193","oldDistrictName":"Thành phố Hạ Long","oldProvinceCode":"22","oldProvinceName":"Tỉnh Quảng Ninh","note":""}],"0762":[{"oldKey":"22-198-06844","oldWardCode":"06844","oldWardType":null,"oldName":"Xã Đồng Tâm","oldDistrictKey":"22-198","oldDistrictName":"Huyện Bình Liêu","oldProvinceCode":"22","oldProvinceName":"Tỉnh Quảng Ninh","note":""},{"oldKey":"22-198-06856","oldWardCode":"06856","oldWardType":null,"oldName":"Xã Lục Hồn","oldDistrictKey":"22-198","oldDistrictName":"Huyện Bình Liêu","oldProvinceCode":"22","oldProvinceName":"Tỉnh Quảng Ninh","note":""}],"0763":[{"oldKey":"22-193-07036","oldWardCode":"07036","oldWardType":null,"oldName":"Xã Đồng Sơn","oldDistrictKey":"22-193","oldDistrictName":"Thành phố Hạ Long","oldProvinceCode":"22","oldProvinceName":"Tỉnh Quảng Ninh","note":""},{"oldKey":"22-202-06985","oldWardCode":"06985","oldWardType":null,"oldName":"Xã Lương Minh","oldDistrictKey":"22-202","oldDistrictName":"Huyện Ba Chẽ","oldProvinceCode":"22","oldProvinceName":"Tỉnh Quảng Ninh","note":""}],"0764":[{"oldKey":"22-205-07105","oldWardCode":"07105","oldWardType":null,"oldName":"Phường Xuân Sơn","oldDistrictKey":"22-205","oldDistrictName":"Thành phố Đông Triều","oldProvinceCode":"22","oldProvinceName":"Tỉnh Quảng Ninh","note":""},{"oldKey":"22-205-07123","oldWardCode":"07123","oldWardType":null,"oldName":"Phường Kim Sơn","oldDistrictKey":"22-205","oldDistrictName":"Thành phố Đông Triều","oldProvinceCode":"22","oldProvinceName":"Tỉnh Quảng Ninh","note":""},{"oldKey":"22-205-07117","oldWardCode":"07117","oldWardType":null,"oldName":"Phường Yên Thọ","oldDistrictKey":"22-205","oldDistrictName":"Thành phố Đông Triều","oldProvinceCode":"22","oldProvinceName":"Tỉnh Quảng Ninh","note":""},{"oldKey":"22-205-07069","oldWardCode":"07069","oldWardType":null,"oldName":"Phường Mạo Khê","oldDistrictKey":"22-205","oldDistrictName":"Thành phố Đông Triều","oldProvinceCode":"22","oldProvinceName":"Tỉnh Quảng Ninh","note":""}],"0766":[{"oldKey":"22-194-06715","oldWardCode":"06715","oldWardType":null,"oldName":"Phường Ninh Dương","oldDistrictKey":"22-194","oldDistrictName":"Thành phố Móng Cái","oldProvinceCode":"22","oldProvinceName":"Tỉnh Quảng Ninh","note":""},{"oldKey":"22-194-06709","oldWardCode":"06709","oldWardType":null,"oldName":"Phường Ka Long","oldDistrictKey":"22-194","oldDistrictName":"Thành phố Móng Cái","oldProvinceCode":"22","oldProvinceName":"Tỉnh Quảng Ninh","note":""},{"oldKey":"22-194-06748","oldWardCode":"06748","oldWardType":null,"oldName":"Xã Vạn Ninh","oldDistrictKey":"22-194","oldDistrictName":"Thành phố Móng Cái","oldProvinceCode":"22","oldProvinceName":"Tỉnh Quảng Ninh","note":""}],"0767":[{"oldKey":"22-194-06736","oldWardCode":"06736","oldWardType":null,"oldName":"Phường Hải Yên","oldDistrictKey":"22-194","oldDistrictName":"Thành phố Móng Cái","oldProvinceCode":"22","oldProvinceName":"Tỉnh Quảng Ninh","note":""},{"oldKey":"22-194-06730","oldWardCode":"06730","oldWardType":null,"oldName":"Xã Hải Đông","oldDistrictKey":"22-194","oldDistrictName":"Thành phố Móng Cái","oldProvinceCode":"22","oldProvinceName":"Tỉnh Quảng Ninh","note":""}],"0768":[{"oldKey":"22-195-06760","oldWardCode":"06760","oldWardType":null,"oldName":"Phường Mông Dương","oldDistrictKey":"22-195","oldDistrictName":"Thành phố Cẩm Phả","oldProvinceCode":"22","oldProvinceName":"Tỉnh Quảng Ninh","note":""},{"oldKey":"22-195-06805","oldWardCode":"06805","oldWardType":null,"oldName":"Xã Dương Huy","oldDistrictKey":"22-195","oldDistrictName":"Thành phố Cẩm Phả","oldProvinceCode":"22","oldProvinceName":"Tỉnh Quảng Ninh","note":""}],"0769":[{"oldKey":"22-206-07165","oldWardCode":"07165","oldWardType":null,"oldName":"Phường Nam Hoà","oldDistrictKey":"22-206","oldDistrictName":"Thị xã Quảng Yên","oldProvinceCode":"22","oldProvinceName":"Tỉnh Quảng Ninh","note":""},{"oldKey":"22-206-07177","oldWardCode":"07177","oldWardType":null,"oldName":"Phường Yên Hải","oldDistrictKey":"22-206","oldDistrictName":"Thị xã Quảng Yên","oldProvinceCode":"22","oldProvinceName":"Tỉnh Quảng Ninh","note":""},{"oldKey":"22-206-07183","oldWardCode":"07183","oldWardType":null,"oldName":"Phường Phong Cốc","oldDistrictKey":"22-206","oldDistrictName":"Thị xã Quảng Yên","oldProvinceCode":"22","oldProvinceName":"Tỉnh Quảng Ninh","note":""},{"oldKey":"22-206-07171","oldWardCode":"07171","oldWardType":null,"oldName":"Xã Cẩm La","oldDistrictKey":"22-206","oldDistrictName":"Thị xã Quảng Yên","oldProvinceCode":"22","oldProvinceName":"Tỉnh Quảng Ninh","note":""}],"0770":[{"oldKey":"22-201-06931","oldWardCode":"06931","oldWardType":null,"oldName":"Xã Quảng Thành","oldDistrictKey":"22-201","oldDistrictName":"Huyện Hải Hà","oldProvinceCode":"22","oldProvinceName":"Tỉnh Quảng Ninh","note":""},{"oldKey":"22-201-06937","oldWardCode":"06937","oldWardType":null,"oldName":"Xã Quảng Thịnh","oldDistrictKey":"22-201","oldDistrictName":"Huyện Hải Hà","oldProvinceCode":"22","oldProvinceName":"Tỉnh Quảng Ninh","note":""},{"oldKey":"22-201-06925","oldWardCode":"06925","oldWardType":null,"oldName":"Xã Quảng Đức","oldDistrictKey":"22-201","oldDistrictName":"Huyện Hải Hà","oldProvinceCode":"22","oldProvinceName":"Tỉnh Quảng Ninh","note":""}],"0772":[{"oldKey":"22-195-06787","oldWardCode":"06787","oldWardType":null,"oldName":"Phường Cẩm Thạch","oldDistrictKey":"22-195","oldDistrictName":"Thành phố Cẩm Phả","oldProvinceCode":"22","oldProvinceName":"Tỉnh Quảng Ninh","note":""},{"oldKey":"22-195-06784","oldWardCode":"06784","oldWardType":null,"oldName":"Phường Cẩm Thủy","oldDistrictKey":"22-195","oldDistrictName":"Thành phố Cẩm Phả","oldProvinceCode":"22","oldProvinceName":"Tỉnh Quảng Ninh","note":""},{"oldKey":"22-195-06778","oldWardCode":"06778","oldWardType":null,"oldName":"Phường Quang Hanh","oldDistrictKey":"22-195","oldDistrictName":"Thành phố Cẩm Phả","oldProvinceCode":"22","oldProvinceName":"Tỉnh Quảng Ninh","note":""}],"0773":[{"oldKey":"22-193-07057","oldWardCode":"07057","oldWardType":null,"oldName":"Xã Bằng Cả","oldDistrictKey":"22-193","oldDistrictName":"Thành phố Hạ Long","oldProvinceCode":"22","oldProvinceName":"Tỉnh Quảng Ninh","note":""},{"oldKey":"22-193-07051","oldWardCode":"07051","oldWardType":null,"oldName":"Xã Dân Chủ","oldDistrictKey":"22-193","oldDistrictName":"Thành phố Hạ Long","oldProvinceCode":"22","oldProvinceName":"Tỉnh Quảng Ninh","note":""},{"oldKey":"22-193-07039","oldWardCode":"07039","oldWardType":null,"oldName":"Xã Tân Dân","oldDistrictKey":"22-193","oldDistrictName":"Thành phố Hạ Long","oldProvinceCode":"22","oldProvinceName":"Tỉnh Quảng Ninh","note":""},{"oldKey":"22-193-07054","oldWardCode":"07054","oldWardType":null,"oldName":"Xã Quảng La","oldDistrictKey":"22-193","oldDistrictName":"Thành phố Hạ Long","oldProvinceCode":"22","oldProvinceName":"Tỉnh Quảng Ninh","note":""}],"0774":[{"oldKey":"22-200-06901","oldWardCode":"06901","oldWardType":null,"oldName":"Xã Quảng An","oldDistrictKey":"22-200","oldDistrictName":"Huyện Đầm Hà","oldProvinceCode":"22","oldProvinceName":"Tỉnh Quảng Ninh","note":""},{"oldKey":"22-200-06910","oldWardCode":"06910","oldWardType":null,"oldName":"Xã Dực Yên","oldDistrictKey":"22-200","oldDistrictName":"Huyện Đầm Hà","oldProvinceCode":"22","oldProvinceName":"Tỉnh Quảng Ninh","note":""},{"oldKey":"22-200-06898","oldWardCode":"06898","oldWardType":null,"oldName":"Xã Quảng Lâm","oldDistrictKey":"22-200","oldDistrictName":"Huyện Đầm Hà","oldProvinceCode":"22","oldProvinceName":"Tỉnh Quảng Ninh","note":""},{"oldKey":"22-200-06913","oldWardCode":"06913","oldWardType":null,"oldName":"Xã Quảng Tân","oldDistrictKey":"22-200","oldDistrictName":"Huyện Đầm Hà","oldProvinceCode":"22","oldProvinceName":"Tỉnh Quảng Ninh","note":""}],"0775":[{"oldKey":"22-206-07162","oldWardCode":"07162","oldWardType":null,"oldName":"Phường Yên Giang","oldDistrictKey":"22-206","oldDistrictName":"Thị xã Quảng Yên","oldProvinceCode":"22","oldProvinceName":"Tỉnh Quảng Ninh","note":""},{"oldKey":"22-206-07132","oldWardCode":"07132","oldWardType":null,"oldName":"Phường Quảng Yên","oldDistrictKey":"22-206","oldDistrictName":"Thị xã Quảng Yên","oldProvinceCode":"22","oldProvinceName":"Tỉnh Quảng Ninh","note":""},{"oldKey":"22-206-07153","oldWardCode":"07153","oldWardType":null,"oldName":"Xã Tiền An","oldDistrictKey":"22-206","oldDistrictName":"Thị xã Quảng Yên","oldProvinceCode":"22","oldProvinceName":"Tỉnh Quảng Ninh","note":""}],"0778":[{"oldKey":"22-193-06706","oldWardCode":"06706","oldWardType":null,"oldName":"Phường Đại Yên","oldDistrictKey":"22-193","oldDistrictName":"Thành phố Hạ Long","oldProvinceCode":"22","oldProvinceName":"Tỉnh Quảng Ninh","note":""},{"oldKey":"22-193-06700","oldWardCode":"06700","oldWardType":null,"oldName":"Phường Tuần Châu","oldDistrictKey":"22-193","oldDistrictName":"Thành phố Hạ Long","oldProvinceCode":"22","oldProvinceName":"Tỉnh Quảng Ninh","note":""},{"oldKey":"22-193-06655","oldWardCode":"06655","oldWardType":null,"oldName":"Phường Hà Khẩu","oldDistrictKey":"22-193","oldDistrictName":"Thành phố Hạ Long","oldProvinceCode":"22","oldProvinceName":"Tỉnh Quảng Ninh","note":""}],"0780":[{"oldKey":"22-203-06994","oldWardCode":"06994","oldWardType":null,"oldName":"Thị trấn Cái Rồng","oldDistrictKey":"22-203","oldDistrictName":"Huyện Vân Đồn","oldProvinceCode":"22","oldProvinceName":"Tỉnh Quảng Ninh","note":""},{"oldKey":"22-203-07018","oldWardCode":"07018","oldWardType":null,"oldName":"Xã Bản Sen","oldDistrictKey":"22-203","oldDistrictName":"Huyện Vân Đồn","oldProvinceCode":"22","oldProvinceName":"Tỉnh Quảng Ninh","note":""},{"oldKey":"22-203-07000","oldWardCode":"07000","oldWardType":null,"oldName":"Xã Bình Dân","oldDistrictKey":"22-203","oldDistrictName":"Huyện Vân Đồn","oldProvinceCode":"22","oldProvinceName":"Tỉnh Quảng Ninh","note":""},{"oldKey":"22-203-06997","oldWardCode":"06997","oldWardType":null,"oldName":"Xã Đài Xuyên","oldDistrictKey":"22-203","oldDistrictName":"Huyện Vân Đồn","oldProvinceCode":"22","oldProvinceName":"Tỉnh Quảng Ninh","note":""},{"oldKey":"22-203-07009","oldWardCode":"07009","oldWardType":null,"oldName":"Xã Đoàn Kết","oldDistrictKey":"22-203","oldDistrictName":"Huyện Vân Đồn","oldProvinceCode":"22","oldProvinceName":"Tỉnh Quảng Ninh","note":""},{"oldKey":"22-203-07015","oldWardCode":"07015","oldWardType":null,"oldName":"Xã Đông Xá","oldDistrictKey":"22-203","oldDistrictName":"Huyện Vân Đồn","oldProvinceCode":"22","oldProvinceName":"Tỉnh Quảng Ninh","note":""},{"oldKey":"22-203-07012","oldWardCode":"07012","oldWardType":null,"oldName":"Xã Hạ Long","oldDistrictKey":"22-203","oldDistrictName":"Huyện Vân Đồn","oldProvinceCode":"22","oldProvinceName":"Tỉnh Quảng Ninh","note":""},{"oldKey":"22-203-07006","oldWardCode":"07006","oldWardType":null,"oldName":"Xã Minh Châu","oldDistrictKey":"22-203","oldDistrictName":"Huyện Vân Đồn","oldProvinceCode":"22","oldProvinceName":"Tỉnh Quảng Ninh","note":""},{"oldKey":"22-203-07027","oldWardCode":"07027","oldWardType":null,"oldName":"Xã Ngọc Vừng","oldDistrictKey":"22-203","oldDistrictName":"Huyện Vân Đồn","oldProvinceCode":"22","oldProvinceName":"Tỉnh Quảng Ninh","note":""},{"oldKey":"22-203-07024","oldWardCode":"07024","oldWardType":null,"oldName":"Xã Quan Lạn","oldDistrictKey":"22-203","oldDistrictName":"Huyện Vân Đồn","oldProvinceCode":"22","oldProvinceName":"Tỉnh Quảng Ninh","note":""},{"oldKey":"22-203-07021","oldWardCode":"07021","oldWardType":null,"oldName":"Xã Thắng Lợi","oldDistrictKey":"22-203","oldDistrictName":"Huyện Vân Đồn","oldProvinceCode":"22","oldProvinceName":"Tỉnh Quảng Ninh","note":""},{"oldKey":"22-203-07003","oldWardCode":"07003","oldWardType":null,"oldName":"Xã Vạn Yên","oldDistrictKey":"22-203","oldDistrictName":"Huyện Vân Đồn","oldProvinceCode":"22","oldProvinceName":"Tỉnh Quảng Ninh","note":""}],"0783":[{"oldKey":"22-194-06754","oldWardCode":"06754","oldWardType":null,"oldName":"Xã Vĩnh Trung","oldDistrictKey":"22-194","oldDistrictName":"Thành phố Móng Cái","oldProvinceCode":"22","oldProvinceName":"Tỉnh Quảng Ninh","note":""},{"oldKey":"22-194-06757","oldWardCode":"06757","oldWardType":null,"oldName":"Xã Vĩnh Thực","oldDistrictKey":"22-194","oldDistrictName":"Thành phố Móng Cái","oldProvinceCode":"22","oldProvinceName":"Tỉnh Quảng Ninh","note":""}],"0784":[{"oldKey":"22-196-06829","oldWardCode":"06829","oldWardType":null,"oldName":"Xã Thượng Yên Công","oldDistrictKey":"22-196","oldDistrictName":"Thành phố Uông Bí","oldProvinceCode":"22","oldProvinceName":"Tỉnh Quảng Ninh","note":""}]}