[{"key":"35-347-13285","code":"13285","districtKey":"35-347","name":"Phường Quang Trung","nameKey":"phuong quang trung"},{"key":"35-347-13291","code":"13291","districtKey":"35-347","name":"Phường Lê Hồng Phong","nameKey":"phuong le hong phong"},{"key":"35-347-13294","code":"13294","districtKey":"35-347","name":"Phường Châu Cầu","nameKey":"phuong chau cau"},{"key":"35-347-13303","code":"13303","districtKey":"35-347","name":"Phường Lam Hạ","nameKey":"phuong lam ha"},{"key":"35-347-13306","code":"13306","districtKey":"35-347","name":"Xã Phù Vân","nameKey":"xa phu van"},{"key":"35-347-13309","code":"13309","districtKey":"35-347","name":"Phường Liêm Chính","nameKey":"phuong liem chinh"},{"key":"35-347-13315","code":"13315","districtKey":"35-347","name":"Phường Thanh Châu","nameKey":"phuong thanh chau"},{"key":"35-347-13318","code":"13318","districtKey":"35-347","name":"Phường Châu Sơn","nameKey":"phuong chau son"},{"key":"35-349-13321","code":"13321","districtKey":"35-349","name":"Phường Đồng Văn","nameKey":"phuong ong van"},{"key":"35-349-13324","code":"13324","districtKey":"35-349","name":"Phường Hòa Mạc","nameKey":"phuong hoa mac"},{"key":"35-349-13327","code":"13327","districtKey":"35-349","name":"Xã Mộc Hoàn","nameKey":"xa moc hoan"},{"key":"35-349-13330","code":"13330","districtKey":"35-349","name":"Phường Châu Giang","nameKey":"phuong chau giang"},{"key":"35-349-13333","code":"13333","districtKey":"35-349","name":"Phường Bạch Thượng","nameKey":"phuong bach thuong"},{"key":"35-349-13336","code":"13336","districtKey":"35-349","name":"Phường Duy Minh","nameKey":"phuong duy minh"},{"key":"35-349-13342","code":"13342","districtKey":"35-349","name":"Phường Duy Hải","nameKey":"phuong duy hai"},{"key":"35-349-13345","code":"13345","districtKey":"35-349","name":"Xã Chuyên Ngoại","nameKey":"xa chuyen ngoai"},{"key":"35-349-13348","code":"13348","districtKey":"35-349","name":"Phường Yên Bắc","nameKey":"phuong yen bac"},{"key":"35-349-13351","code":"13351","districtKey":"35-349","name":"Xã Trác Văn","nameKey":"xa trac van"},{"key":"35-349-13354","code":"13354","districtKey":"35-349","name":"Phường Tiên Nội","nameKey":"phuong tien noi"},{"key":"35-349-13357","code":"13357","districtKey":"35-349","name":"Phường Hoàng Đông","nameKey":"phuong hoang ong"},{"key":"35-349-13360","code":"13360","districtKey":"35-349","name":"Xã Yên Nam","nameKey":"xa yen nam"},{"key":"35-349-13363","code":"13363","districtKey":"35-349","name":"Xã Tiên Ngoại","nameKey":"xa tien ngoai"},{"key":"35-347-13366","code":"13366","districtKey":"35-347","name":"Phường Tân Hiệp","nameKey":"phuong tan hiep"},{"key":"35-349-13369","code":"13369","districtKey":"35-349","name":"Xã Tiên Sơn","nameKey":"xa tien son"},{"key":"35-350-13384","code":"13384","districtKey":"35-350","name":"Phường Quế","nameKey":"phuong que"},{"key":"35-350-13387","code":"13387","districtKey":"35-350","name":"Xã Nguyễn Úy","nameKey":"xa nguyen uy"},{"key":"35-350-13390","code":"13390","districtKey":"35-350","name":"Phường Đại Cương","nameKey":"phuong ai cuong"},{"key":"35-350-13393","code":"13393","districtKey":"35-350","name":"Phường Lê Hồ","nameKey":"phuong le ho"},{"key":"35-350-13396","code":"13396","districtKey":"35-350","name":"Phường Tượng Lĩnh","nameKey":"phuong tuong linh"},{"key":"35-350-13402","code":"13402","districtKey":"35-350","name":"Phường Tân Tựu","nameKey":"phuong tan tuu"},{"key":"35-350-13405","code":"13405","districtKey":"35-350","name":"Phường Đồng Hóa","nameKey":"phuong ong hoa"},{"key":"35-350-13408","code":"13408","districtKey":"35-350","name":"Xã Hoàng Tây","nameKey":"xa hoang tay"},{"key":"35-350-13411","code":"13411","districtKey":"35-350","name":"Phường Tân Sơn","nameKey":"phuong tan son"},{"key":"35-350-13414","code":"13414","districtKey":"35-350","name":"Xã Thụy Lôi","nameKey":"xa thuy loi"},{"key":"35-350-13417","code":"13417","districtKey":"35-350","name":"Xã Văn Xá","nameKey":"xa van xa"},{"key":"35-350-13420","code":"13420","districtKey":"35-350","name":"Xã Khả Phong","nameKey":"xa kha phong"},{"key":"35-350-13423","code":"13423","districtKey":"35-350","name":"Phường Ngọc Sơn","nameKey":"phuong ngoc son"},{"key":"35-347-13426","code":"13426","districtKey":"35-347","name":"Xã Kim Bình","nameKey":"xa kim binh"},{"key":"35-350-13429","code":"13429","districtKey":"35-350","name":"Phường Ba Sao","nameKey":"phuong ba sao"},{"key":"35-350-13432","code":"13432","districtKey":"35-350","name":"Xã Liên Sơn","nameKey":"xa lien son"},{"key":"35-350-13435","code":"13435","districtKey":"35-350","name":"Phường Thi Sơn","nameKey":"phuong thi son"},{"key":"35-350-13438","code":"13438","districtKey":"35-350","name":"Xã Thanh Sơn","nameKey":"xa thanh son"},{"key":"35-351-13441","code":"13441","districtKey":"35-351","name":"Thị trấn Kiện Khê","nameKey":"thi tran kien khe"},{"key":"35-347-13444","code":"13444","districtKey":"35-347","name":"Phường Tân Liêm","nameKey":"phuong tan liem"},{"key":"35-351-13450","code":"13450","districtKey":"35-351","name":"Xã Liêm Phong","nameKey":"xa liem phong"},{"key":"35-351-13453","code":"13453","districtKey":"35-351","name":"Xã Thanh Hà","nameKey":"xa thanh ha"},{"key":"35-351-13456","code":"13456","districtKey":"35-351","name":"Xã Liêm Cần","nameKey":"xa liem can"},{"key":"35-347-13459","code":"13459","districtKey":"35-347","name":"Phường Thanh Tuyền","nameKey":"phuong thanh tuyen"},{"key":"35-351-13465","code":"13465","districtKey":"35-351","name":"Xã Liêm Thuận","nameKey":"xa liem thuan"},{"key":"35-351-13468","code":"13468","districtKey":"35-351","name":"Xã Thanh Thủy","nameKey":"xa thanh thuy"},{"key":"35-351-13471","code":"13471","districtKey":"35-351","name":"Xã Thanh Phong","nameKey":"xa thanh phong"},{"key":"35-351-13474","code":"13474","districtKey":"35-351","name":"Thị trấn Tân Thanh","nameKey":"thi tran tan thanh"},{"key":"35-351-13477","code":"13477","districtKey":"35-351","name":"Xã Thanh Tân","nameKey":"xa thanh tan"},{"key":"35-351-13480","code":"13480","districtKey":"35-351","name":"Xã Liêm Túc","nameKey":"xa liem tuc"},{"key":"35-351-13483","code":"13483","districtKey":"35-351","name":"Xã Liêm Sơn","nameKey":"xa liem son"},{"key":"35-351-13486","code":"13486","districtKey":"35-351","name":"Xã Thanh Hương","nameKey":"xa thanh huong"},{"key":"35-351-13489","code":"13489","districtKey":"35-351","name":"Xã Thanh Nghị","nameKey":"xa thanh nghi"},{"key":"35-351-13492","code":"13492","districtKey":"35-351","name":"Xã Thanh Tâm","nameKey":"xa thanh tam"},{"key":"35-351-13495","code":"13495","districtKey":"35-351","name":"Xã Thanh Nguyên","nameKey":"xa thanh nguyen"},{"key":"35-351-13498","code":"13498","districtKey":"35-351","name":"Xã Thanh Hải","nameKey":"xa thanh hai"},{"key":"35-352-13501","code":"13501","districtKey":"35-352","name":"Thị trấn Bình Mỹ","nameKey":"thi tran binh my"},{"key":"35-352-13504","code":"13504","districtKey":"35-352","name":"Xã Bình Nghĩa","nameKey":"xa binh nghia"},{"key":"35-347-13507","code":"13507","districtKey":"35-347","name":"Xã Đinh Xá","nameKey":"xa inh xa"},{"key":"35-352-13510","code":"13510","districtKey":"35-352","name":"Xã Tràng An","nameKey":"xa trang an"},{"key":"35-347-13513","code":"13513","districtKey":"35-347","name":"Xã Trịnh Xá","nameKey":"xa trinh xa"},{"key":"35-352-13516","code":"13516","districtKey":"35-352","name":"Xã Đồng Du","nameKey":"xa ong du"},{"key":"35-352-13519","code":"13519","districtKey":"35-352","name":"Xã Ngọc Lũ","nameKey":"xa ngoc lu"},{"key":"35-352-13525","code":"13525","districtKey":"35-352","name":"Xã Đồn Xá","nameKey":"xa on xa"},{"key":"35-352-13528","code":"13528","districtKey":"35-352","name":"Xã An Ninh","nameKey":"xa an ninh"},{"key":"35-352-13531","code":"13531","districtKey":"35-352","name":"Xã Bồ Đề","nameKey":"xa bo e"},{"key":"35-352-13540","code":"13540","districtKey":"35-352","name":"Xã Bình An","nameKey":"xa binh an"},{"key":"35-352-13543","code":"13543","districtKey":"35-352","name":"Xã Vũ Bản","nameKey":"xa vu ban"},{"key":"35-352-13546","code":"13546","districtKey":"35-352","name":"Xã Trung Lương","nameKey":"xa trung luong"},{"key":"35-352-13552","code":"13552","districtKey":"35-352","name":"Xã An Đổ","nameKey":"xa an o"},{"key":"35-352-13555","code":"13555","districtKey":"35-352","name":"Xã La Sơn","nameKey":"xa la son"},{"key":"35-352-13558","code":"13558","districtKey":"35-352","name":"Xã Tiêu Động","nameKey":"xa tieu ong"},{"key":"35-352-13561","code":"13561","districtKey":"35-352","name":"Xã An Lão","nameKey":"xa an lao"},{"key":"35-353-13567","code":"13567","districtKey":"35-353","name":"Xã Hợp Lý","nameKey":"xa hop ly"},{"key":"35-353-13570","code":"13570","districtKey":"35-353","name":"Xã Nguyên Lý","nameKey":"xa nguyen ly"},{"key":"35-353-13573","code":"13573","districtKey":"35-353","name":"Xã Chính Lý","nameKey":"xa chinh ly"},{"key":"35-353-13576","code":"13576","districtKey":"35-353","name":"Xã Chân Lý","nameKey":"xa chan ly"},{"key":"35-353-13579","code":"13579","districtKey":"35-353","name":"Xã Đạo Lý","nameKey":"xa ao ly"},{"key":"35-353-13582","code":"13582","districtKey":"35-353","name":"Xã Công Lý","nameKey":"xa cong ly"},{"key":"35-353-13585","code":"13585","districtKey":"35-353","name":"Xã Văn Lý","nameKey":"xa van ly"},{"key":"35-353-13588","code":"13588","districtKey":"35-353","name":"Xã Bắc Lý","nameKey":"xa bac ly"},{"key":"35-353-13591","code":"13591","districtKey":"35-353","name":"Xã Đức Lý","nameKey":"xa uc ly"},{"key":"35-353-13594","code":"13594","districtKey":"35-353","name":"Xã Trần Hưng Đạo","nameKey":"xa tran hung ao"},{"key":"35-353-13597","code":"13597","districtKey":"35-353","name":"Thị trấn Vĩnh Trụ","nameKey":"thi tran vinh tru"},{"key":"35-353-13600","code":"13600","districtKey":"35-353","name":"Xã Nhân Thịnh","nameKey":"xa nhan thinh"},{"key":"35-353-13606","code":"13606","districtKey":"35-353","name":"Xã Nhân Khang","nameKey":"xa nhan khang"},{"key":"35-353-13609","code":"13609","districtKey":"35-353","name":"Xã Nhân Mỹ","nameKey":"xa nhan my"},{"key":"35-353-13612","code":"13612","districtKey":"35-353","name":"Xã Nhân Nghĩa","nameKey":"xa nhan nghia"},{"key":"35-353-13615","code":"13615","districtKey":"35-353","name":"Xã Nhân Chính","nameKey":"xa nhan chinh"},{"key":"35-353-13618","code":"13618","districtKey":"35-353","name":"Xã Nhân Bình","nameKey":"xa nhan binh"},{"key":"35-353-13621","code":"13621","districtKey":"35-353","name":"Xã Phú Phúc","nameKey":"xa phu phuc"},{"key":"35-353-13624","code":"13624","districtKey":"35-353","name":"Xã Xuân Khê","nameKey":"xa xuan khe"},{"key":"35-353-13627","code":"13627","districtKey":"35-353","name":"Xã Tiến Thắng","nameKey":"xa tien thang"},{"key":"35-353-13630","code":"13630","districtKey":"35-353","name":"Xã Hòa Hậu","nameKey":"xa hoa hau"}]